pydeps/__init__.py
pydeps/__main__.py
pydeps/arguments.py
pydeps/cli.py
pydeps/colors.py
pydeps/configs.py
pydeps/depgraph.py
pydeps/depgraph2dot.py
pydeps/dot.py
pydeps/dummymodule.py
pydeps/mf27.py
pydeps/mfimp.py
pydeps/package_names.py
pydeps/py2depgraph.py
pydeps/pycompat.py
pydeps/pydeps.py
pydeps/pystdlib.py
pydeps/render_context.py
pydeps/target.py
pydeps-3.0.2.dist-info/licenses/LICENSE
pydeps-3.0.2.dist-info/METADATA
pydeps-3.0.2.dist-info/WHEEL
pydeps-3.0.2.dist-info/entry_points.txt
pydeps-3.0.2.dist-info/top_level.txt
pydeps-3.0.2.dist-info/RECORD
